SJNET/__init__.py
SJNET/main.py
SJNET-2.2.0.dist-info/METADATA
SJNET-2.2.0.dist-info/WHEEL
SJNET-2.2.0.dist-info/top_level.txt
SJNET-2.2.0.dist-info/RECORD
